Metadata-Version: 2.1
Name: santisossalibrary
Version: 0.0.1
Summary: A very basic calculator
Home-page: 
Author: Santiago Sossa
Author-email: santisossa67@gmail.com
License: MIT
Keywords: calculator
Classifier: Development Status :: 5 - Production/Stable
Classifier: Intended Audience :: Education
Classifier: Operating System :: Unix
Classifier: License :: OSI Approved :: MIT License
Classifier: Programming Language :: Python :: 3
License-File: LICENCE.txt
